auk/__init__.py
auk/compiler.py
auk/nodes.py
auk/predicate.yml
auk-0.1.1.dist-info/METADATA
auk-0.1.1.dist-info/RECORD
auk-0.1.1.dist-info/WHEEL
auk-0.1.1.dist-info/top_level.txt
tests/__init__.py
tests/argnames.py
tests/compiler.py
tests/examples.py
tests/nodes.py
