Metadata-Version: 2.1
Name: auk
Version: 0.1.1
Summary: Micro-package for compiling s-expressions into Python's predicate functions
Home-page: http://github.com/IwoHerka/auk
Author: Iwo Herka
Author-email: hi@iwoherka.eu
Maintainer: Iwo Herka
Maintainer-email: hi@iwoherka.eu
License: MIT
Platform: UNKNOWN
Classifier: Development Status :: 3 - Alpha
Classifier: Intended Audience :: Developers
Classifier: Programming Language :: Python
Requires: python (>= 3.4)
Provides: auk
Requires-Dist: sexpr
